{
  "fill" : {
    "automatic-gradient" : "display-p3:0.89804,0.85098,0.76471,1.00000",
    "orientation" : {
      "start" : {
        "x" : 0.5,
        "y" : 1
      },
      "stop" : {
        "x" : 0.5,
        "y" : 0.3
      }
    }
  },
  "groups" : [
    {
      "layers" : [
        {
          "blend-mode" : "normal",
          "fill" : {
            "solid" : "srgb:0.99216,0.98431,0.96863,1.00000"
          },
          "glass" : true,
          "image-name" : "quote.bubble.fill@3x 2.png",
          "name" : "quote.bubble.fill@3x 2",
          "position" : {
            "scale" : 1,
            "translation-in-points" : [
              130.16463215735803,
              -150.86247089063136
            ]
          }
        }
      ],
      "shadow" : {
        "kind" : "neutral",
        "opacity" : 0.5
      },
      "translucency" : {
        "enabled" : true,
        "value" : 0.5
      }
    }
  ],
  "supported-platforms" : {
    "circles" : [
      "watchOS"
    ],
    "squares" : "shared"
  }
}